malanka/__init__.py
malanka-0.1.1.dist-info/LICENSE
malanka-0.1.1.dist-info/WHEEL
malanka-0.1.1.dist-info/METADATA
malanka-0.1.1.dist-info/RECORD
