Metadata-Version: 2.1
Name: malanka
Version: 0.1.1
Summary: WebSocket channels.
Home-page: https://github.com/alex-oleshkevich/malanka
License: MIT
Keywords: websocket,channels,real-time,starlette,fastapi,asgi
Author: alex.oleshkevich
Author-email: alex.oleshkevich@gmail.com
Requires-Python: >=3.6.2,<4.0.0
Classifier: Development Status :: 1 - Planning
Classifier: Environment :: Web Environment
Classifier: Intended Audience :: Developers
Classifier: License :: OSI Approved :: MIT License
Classifier: Operating System :: OS Independent
Classifier: Programming Language :: Python :: 3
Classifier: Programming Language :: Python :: 3.10
Classifier: Programming Language :: Python :: 3.6
Classifier: Programming Language :: Python :: 3.7
Classifier: Programming Language :: Python :: 3.8
Classifier: Programming Language :: Python :: 3.9
Classifier: Topic :: Software Development :: Libraries :: Python Modules
Classifier: Typing :: Typed
Project-URL: Documentation, https://github.com/alex-oleshkevich/malanka
Project-URL: Repository, https://github.com/alex-oleshkevich/malanka
